rdflib_wsdl/__init__.py
rdflib_wsdl/methods_specification.py
rdflib_wsdl/parser.py
rdflib_wsdl/shared.py
rdflib_wsdl/wsdl2rdf.py
rdflib_wsdl/wsdl_components.py
rdflib_wsdl/xmlhandler.py
rdflib_wsdl/xmlhandler_mainbody.py
rdflib_wsdl/extensions/__init__.py
rdflib_wsdl/extensions/binding.py
rdflib_wsdl/extensions/types.py
test/__init__.py
test/conftest.py
test/examplecases/__init__.py
test/examplecases/test_compare_wsdl_ttl.py
test/examplecases/ex1/__init__.py
rdflib_wsdl-0.1.dist-info/LICENSE
rdflib_wsdl-0.1.dist-info/METADATA
rdflib_wsdl-0.1.dist-info/WHEEL
rdflib_wsdl-0.1.dist-info/entry_points.txt
rdflib_wsdl-0.1.dist-info/top_level.txt
rdflib_wsdl-0.1.dist-info/RECORD
