Metadata-Version: 2.1
Name: rdflib-wsdl
Version: 0.1
Summary: Parser for wsdl as plugin for rdflib
Author: Richard Focke Fechner
Author-email: richardfechner@posteo.net
Project-URL: Homepage, https://github.com/WhiteGobo/rdflib_wsdl
Classifier: Programming Language :: Python :: 3
Classifier: Operating System :: OS Independent
License-File: LICENSE
Requires-Dist: rdflib
